Workbook

Sheet ITEM MASTER
A1: ITEM CODE | B1: PRODUCT NAME | C1: BRAND | D1: CATEGORY | E1: PACK SIZE | F1: PACK UNIT | G1: BASE UNIT | H1: UNIT PER CARTON | I1: PURCHASE RATE | J1: SALE RATE | K1: OPENING STOCK | L1: REORDER LEVEL | M1: SUPPLIER | N1: STATUS
A2: ATH-001 | B2: HONDA ATLAS | C2: HD 50 DD | D2: ENGINE OIL | E2: 1 | F2: LITRE | G2: BOTTLE | H2: 12 | I2: 400 | K2: 0 | L2: 20 | N2: ACTIVE
A3: ATH-002 | B3: HAVOLINE | C3: HD 50 DD | D3: ENGINE OIL | E3: 1 | F3: LITRE | G3: BOTTLE | H3: 12 | I3: 404.166 | K3: 0 | L3: 20 | N3: ACTIVE
A4: ATH-003 | B4: HONDA ATLAS | C4: HD 50 DD | D4: ENGINE OIL | E4: 700 | F4: ML | G4: BOTTLE | H4: 12 | I4: 325 | K4: 0 | L4: 30 | N4: ACTIVE
A5: ATH-004 | B5: HAVOLINE | C5: HD 50 DD | D5: ENGINE OIL | E5: 700 | F5: ML | G5: BOTTLE | H5: 12 | I5: 329.166 | K5: 0 | L5: 30 | N5: ACTIVE
A6: ATH-005 | B6: SHELL | C6: HD 50 DD | D6: ENGINE OIL | E6: 700 | F6: ML | G6: BOTTLE | H6: 12 | I6: 312.5 | K6: 0 | L6: 5 | N6: ACTIVE
A7: ATH-006 | B7: DYL LUBE | C7: HD 50 DD | D7: ENGINE OIL | E7: 800 | F7: ML | G7: BOTTLE | H7: 12 | I7: 310 | K7: 0 | L7: 5 | N7: ACTIVE

Sheet PURCHASE
A1: PURCHASE ID | B1: DATE | C1: SUPPLIER | D1: INVOICE NUMBER | E1: ITEM CODE | F1: PRODUCT NAME | G1: PURCHASE UNIT | H1: QUANTITY | I1: RATE | J1: TOTAL AMOUNT | K1: CONVERSION | L1: BASE QUANTITY | M1: PAYMENT STATUS | N1: PAID AMOUNT | O1: PAYABLE | P1: REMARKS
A2: =IF(B2="","","PUR-"&TEXT(ROW()-1,"0000")) -> PUR-0001 | B2: 46301 | C2: MALIK AYAN SAJID | E2: ATH-001 | F2: =+IFERROR(_xlfn.XLOOKUP(E2,'ITEM MASTER'!$A:$A,'ITEM MASTER'!$B:$B,""),"") -> HONDA ATLAS | G2: CARTON | H2: 10 | I2: =IFERROR(_xlfn.XLOOKUP(E2,'ITEM MASTER'!$A:$A,'ITEM MASTER'!$I:$I,"")*IF(G2="CARTON",_xlfn.XLOOKUP(E2,'ITEM MASTER'!$A:$A,'ITEM MASTER'!$H:$H,1),1),"") -> 4800 | J2: =IF(OR(H2="",12=""),"",H2*I2) -> 48000 | K2: =IFERROR(_xlfn.XLOOKUP(E2,'ITEM MASTER'!$A:$A,'ITEM MASTER'!$H:$H,""),"") -> 12 | L2: =IF(OR(G2="",H2=""),"",IF(G2="BOTTLE",H2,IF(G2="CARTON",H2*K2,H2))) -> 120 | M2: PARTIAL | N2: 40000 | O2: =IF(J2="","",J2-N2) -> 8000
A3: =IF(B3="","","PUR-"&TEXT(ROW()-1,"0000")) | F3: =+IFERROR(_xlfn.XLOOKUP(E3,'ITEM MASTER'!$A:$A,'ITEM MASTER'!$B:$B,""),"") -> 0 | I3: =IFERROR(_xlfn.XLOOKUP(E3,'ITEM MASTER'!$A:$A,'ITEM MASTER'!$I:$I,"")*IF(G3="CARTON",_xlfn.XLOOKUP(E3,'ITEM MASTER'!$A:$A,'ITEM MASTER'!$H:$H,1),1),"") -> 0 | J3: =IF(OR(H3="",12=""),"",H3*I3) | K3: =IFERROR(_xlfn.XLOOKUP(E3,'ITEM MASTER'!$A:$A,'ITEM MASTER'!$H:$H,""),"") -> 0 | L3: =IF(OR(G3="",H3=""),"",IF(G3="BOTTLE",H3,IF(G3="CARTON",H3*K3,H3))) | O3: =IF(J3="","",J3-N3)
A4: =IF(B4="","","PUR-"&TEXT(ROW()-1,"0000")) | F4: =+IFERROR(_xlfn.XLOOKUP(E4,'ITEM MASTER'!$A:$A,'ITEM MASTER'!$B:$B,""),"") -> 0 | I4: =IFERROR(_xlfn.XLOOKUP(E4,'ITEM MASTER'!$A:$A,'ITEM MASTER'!$I:$I,"")*IF(G4="CARTON",_xlfn.XLOOKUP(E4,'ITEM MASTER'!$A:$A,'ITEM MASTER'!$H:$H,1),1),"") -> 0 | J4: =IF(OR(H4="",12=""),"",H4*I4) | K4: =IFERROR(_xlfn.XLOOKUP(E4,'ITEM MASTER'!$A:$A,'ITEM MASTER'!$H:$H,""),"") -> 0 | L4: =IF(OR(G4="",H4=""),"",IF(G4="BOTTLE",H4,IF(G4="CARTON",H4*K4,H4))) | O4: =IF(J4="","",J4-N4)
A5: =IF(B5="","","PUR-"&TEXT(ROW()-1,"0000")) | F5: =+IFERROR(_xlfn.XLOOKUP(E5,'ITEM MASTER'!$A:$A,'ITEM MASTER'!$B:$B,""),"") -> 0 | I5: =IFERROR(_xlfn.XLOOKUP(E5,'ITEM MASTER'!$A:$A,'ITEM MASTER'!$I:$I,"")*IF(G5="CARTON",_xlfn.XLOOKUP(E5,'ITEM MASTER'!$A:$A,'ITEM MASTER'!$H:$H,1),1),"") -> 0 | J5: =IF(OR(H5="",12=""),"",H5*I5) | K5: =IFERROR(_xlfn.XLOOKUP(E5,'ITEM MASTER'!$A:$A,'ITEM MASTER'!$H:$H,""),"") -> 0 | L5: =IF(OR(G5="",H5=""),"",IF(G5="BOTTLE",H5,IF(G5="CARTON",H5*K5,H5))) | O5: =IF(J5="","",J5-N5)
A6: =IF(B6="","","PUR-"&TEXT(ROW()-1,"0000")) | F6: =+IFERROR(_xlfn.XLOOKUP(E6,'ITEM MASTER'!$A:$A,'ITEM MASTER'!$B:$B,""),"") -> 0 | I6: =IFERROR(_xlfn.XLOOKUP(E6,'ITEM MASTER'!$A:$A,'ITEM MASTER'!$I:$I,"")*IF(G6="CARTON",_xlfn.XLOOKUP(E6,'ITEM MASTER'!$A:$A,'ITEM MASTER'!$H:$H,1),1),"") -> 0 | J6: =IF(OR(H6="",12=""),"",H6*I6) | K6: =IFERROR(_xlfn.XLOOKUP(E6,'ITEM MASTER'!$A:$A,'ITEM MASTER'!$H:$H,""),"") -> 0 | L6: =IF(OR(G6="",H6=""),"",IF(G6="BOTTLE",H6,IF(G6="CARTON",H6*K6,H6))) | O6: =IF(J6="","",J6-N6)
A7: =IF(B7="","","PUR-"&TEXT(ROW()-1,"0000")) | F7: =+IFERROR(_xlfn.XLOOKUP(E7,'ITEM MASTER'!$A:$A,'ITEM MASTER'!$B:$B,""),"") -> 0 | I7: =IFERROR(_xlfn.XLOOKUP(E7,'ITEM MASTER'!$A:$A,'ITEM MASTER'!$I:$I,"")*IF(G7="CARTON",_xlfn.XLOOKUP(E7,'ITEM MASTER'!$A:$A,'ITEM MASTER'!$H:$H,1),1),"") -> 0 | J7: =IF(OR(H7="",12=""),"",H7*I7) | K7: =IFERROR(_xlfn.XLOOKUP(E7,'ITEM MASTER'!$A:$A,'ITEM MASTER'!$H:$H,""),"") -> 0 | L7: =IF(OR(G7="",H7=""),"",IF(G7="BOTTLE",H7,IF(G7="CARTON",H7*K7,H7))) | O7: =IF(J7="","",J7-N7)
A8: =IF(B8="","","PUR-"&TEXT(ROW()-1,"0000")) | F8: =+IFERROR(_xlfn.XLOOKUP(E8,'ITEM MASTER'!$A:$A,'ITEM MASTER'!$B:$B,""),"") -> 0 | I8: =IFERROR(_xlfn.XLOOKUP(E8,'ITEM MASTER'!$A:$A,'ITEM MASTER'!$I:$I,"")*IF(G8="CARTON",_xlfn.XLOOKUP(E8,'ITEM MASTER'!$A:$A,'ITEM MASTER'!$H:$H,1),1),"") -> 0 | J8: =IF(OR(H8="",12=""),"",H8*I8) | K8: =IFERROR(_xlfn.XLOOKUP(E8,'ITEM MASTER'!$A:$A,'ITEM MASTER'!$H:$H,""),"") -> 0 | L8: =IF(OR(G8="",H8=""),"",IF(G8="BOTTLE",H8,IF(G8="CARTON",H8*K8,H8))) | O8: =IF(J8="","",J8-N8)
A9: =IF(B9="","","PUR-"&TEXT(ROW()-1,"0000")) -> PUR-0008 | B9: 46301 | E9: ATH-003 | F9: =+IFERROR(_xlfn.XLOOKUP(E9,'ITEM MASTER'!$A:$A,'ITEM MASTER'!$B:$B,""),"") -> HONDA ATLAS | G9: CARTON | H9: 10 | I9: =IFERROR(_xlfn.XLOOKUP(E9,'ITEM MASTER'!$A:$A,'ITEM MASTER'!$I:$I,"")*IF(G9="CARTON",_xlfn.XLOOKUP(E9,'ITEM MASTER'!$A:$A,'ITEM MASTER'!$H:$H,1),1),"") -> 3900 | J9: =IF(OR(H9="",12=""),"",H9*I9) -> 39000 | K9: =IFERROR(_xlfn.XLOOKUP(E9,'ITEM MASTER'!$A:$A,'ITEM MASTER'!$H:$H,""),"") -> 12 | L9: =IF(OR(G9="",H9=""),"",IF(G9="BOTTLE",H9,IF(G9="CARTON",H9*K9,H9))) -> 120 | M9: PAID | N9: 39000 | O9: =IF(J9="","",J9-N9) -> 0
A10: =IF(B10="","","PUR-"&TEXT(ROW()-1,"0000")) | F10: =+IFERROR(_xlfn.XLOOKUP(E10,'ITEM MASTER'!$A:$A,'ITEM MASTER'!$B:$B,""),"") -> 0 | I10: =IFERROR(_xlfn.XLOOKUP(E10,'ITEM MASTER'!$A:$A,'ITEM MASTER'!$I:$I,"")*IF(G10="CARTON",_xlfn.XLOOKUP(E10,'ITEM MASTER'!$A:$A,'ITEM MASTER'!$H:$H,1),1),"") -> 0 | J10: =IF(OR(H10="",12=""),"",H10*I10) | K10: =IFERROR(_xlfn.XLOOKUP(E10,'ITEM MASTER'!$A:$A,'ITEM MASTER'!$H:$H,""),"") -> 0 | L10: =IF(OR(G10="",H10=""),"",IF(G10="BOTTLE",H10,IF(G10="CARTON",H10*K10,H10))) | O10: =IF(J10="","",J10-N10)
A11: =IF(B11="","","PUR-"&TEXT(ROW()-1,"0000")) | F11: =+IFERROR(_xlfn.XLOOKUP(E11,'ITEM MASTER'!$A:$A,'ITEM MASTER'!$B:$B,""),"") -> 0 | I11: =IFERROR(_xlfn.XLOOKUP(E11,'ITEM MASTER'!$A:$A,'ITEM MASTER'!$I:$I,"")*IF(G11="CARTON",_xlfn.XLOOKUP(E11,'ITEM MASTER'!$A:$A,'ITEM MASTER'!$H:$H,1),1),"") -> 0 | J11: =IF(OR(H11="",12=""),"",H11*I11) | K11: =IFERROR(_xlfn.XLOOKUP(E11,'ITEM MASTER'!$A:$A,'ITEM MASTER'!$H:$H,""),"") -> 0 | L11: =IF(OR(G11="",H11=""),"",IF(G11="BOTTLE",H11,IF(G11="CARTON",H11*K11,H11))) | O11: =IF(J11="","",J11-N11)
A12: =IF(B12="","","PUR-"&TEXT(ROW()-1,"0000")) | F12: =+IFERROR(_xlfn.XLOOKUP(E12,'ITEM MASTER'!$A:$A,'ITEM MASTER'!$B:$B,""),"") -> 0 | I12: =IFERROR(_xlfn.XLOOKUP(E12,'ITEM MASTER'!$A:$A,'ITEM MASTER'!$I:$I,"")*IF(G12="CARTON",_xlfn.XLOOKUP(E12,'ITEM MASTER'!$A:$A,'ITEM MASTER'!$H:$H,1),1),"") -> 0 | J12: =IF(OR(H12="",12=""),"",H12*I12) | K12: =IFERROR(_xlfn.XLOOKUP(E12,'ITEM MASTER'!$A:$A,'ITEM MASTER'!$H:$H,""),"") -> 0 | L12: =IF(OR(G12="",H12=""),"",IF(G12="BOTTLE",H12,IF(G12="CARTON",H12*K12,H12))) | O12: =IF(J12="","",J12-N12)
A13: =IF(B13="","","PUR-"&TEXT(ROW()-1,"0000")) | F13: =+IFERROR(_xlfn.XLOOKUP(E13,'ITEM MASTER'!$A:$A,'ITEM MASTER'!$B:$B,""),"") -> 0 | I13: =IFERROR(_xlfn.XLOOKUP(E13,'ITEM MASTER'!$A:$A,'ITEM MASTER'!$I:$I,"")*IF(G13="CARTON",_xlfn.XLOOKUP(E13,'ITEM MASTER'!$A:$A,'ITEM MASTER'!$H:$H,1),1),"") -> 0 | J13: =IF(OR(H13="",12=""),"",H13*I13) | K13: =IFERROR(_xlfn.XLOOKUP(E13,'ITEM MASTER'!$A:$A,'ITEM MASTER'!$H:$H,""),"") -> 0 | L13: =IF(OR(G13="",H13=""),"",IF(G13="BOTTLE",H13,IF(G13="CARTON",H13*K13,H13))) | O13: =IF(J13="","",J13-N13)
A14: =IF(B14="","","PUR-"&TEXT(ROW()-1,"0000")) | F14: =+IFERROR(_xlfn.XLOOKUP(E14,'ITEM MASTER'!$A:$A,'ITEM MASTER'!$B:$B,""),"") -> 0 | I14: =IFERROR(_xlfn.XLOOKUP(E14,'ITEM MASTER'!$A:$A,'ITEM MASTER'!$I:$I,"")*IF(G14="CARTON",_xlfn.XLOOKUP(E14,'ITEM MASTER'!$A:$A,'ITEM MASTER'!$H:$H,1),1),"") -> 0 | J14: =IF(OR(H14="",12=""),"",H14*I14) | K14: =IFERROR(_xlfn.XLOOKUP(E14,'ITEM MASTER'!$A:$A,'ITEM MASTER'!$H:$H,""),"") -> 0 | L14: =IF(OR(G14="",H14=""),"",IF(G14="BOTTLE",H14,IF(G14="CARTON",H14*K14,H14))) | O14: =IF(J14="","",J14-N14)
A15: =IF(B15="","","PUR-"&TEXT(ROW()-1,"0000")) | F15: =+IFERROR(_xlfn.XLOOKUP(E15,'ITEM MASTER'!$A:$A,'ITEM MASTER'!$B:$B,""),"") -> 0 | I15: =IFERROR(_xlfn.XLOOKUP(E15,'ITEM MASTER'!$A:$A,'ITEM MASTER'!$I:$I,"")*IF(G15="CARTON",_xlfn.XLOOKUP(E15,'ITEM MASTER'!$A:$A,'ITEM MASTER'!$H:$H,1),1),"") -> 0 | J15: =IF(OR(H15="",12=""),"",H15*I15) | K15: =IFERROR(_xlfn.XLOOKUP(E15,'ITEM MASTER'!$A:$A,'ITEM MASTER'!$H:$H,""),"") -> 0 | L15: =IF(OR(G15="",H15=""),"",IF(G15="BOTTLE",H15,IF(G15="CARTON",H15*K15,H15))) | O15: =IF(J15="","",J15-N15)
A16: =IF(B16="","","PUR-"&TEXT(ROW()-1,"0000")) | F16: =+IFERROR(_xlfn.XLOOKUP(E16,'ITEM MASTER'!$A:$A,'ITEM MASTER'!$B:$B,""),"") -> 0 | I16: =IFERROR(_xlfn.XLOOKUP(E16,'ITEM MASTER'!$A:$A,'ITEM MASTER'!$I:$I,"")*IF(G16="CARTON",_xlfn.XLOOKUP(E16,'ITEM MASTER'!$A:$A,'ITEM MASTER'!$H:$H,1),1),"") -> 0 | J16: =IF(OR(H16="",12=""),"",H16*I16) | K16: =IFERROR(_xlfn.XLOOKUP(E16,'ITEM MASTER'!$A:$A,'ITEM MASTER'!$H:$H,""),"") -> 0 | L16: =IF(OR(G16="",H16=""),"",IF(G16="BOTTLE",H16,IF(G16="CARTON",H16*K16,H16))) | O16: =IF(J16="","",J16-N16)
A17: =IF(B17="","","PUR-"&TEXT(ROW()-1,"0000")) | F17: =+IFERROR(_xlfn.XLOOKUP(E17,'ITEM MASTER'!$A:$A,'ITEM MASTER'!$B:$B,""),"") -> 0 | I17: =IFERROR(_xlfn.XLOOKUP(E17,'ITEM MASTER'!$A:$A,'ITEM MASTER'!$I:$I,"")*IF(G17="CARTON",_xlfn.XLOOKUP(E17,'ITEM MASTER'!$A:$A,'ITEM MASTER'!$H:$H,1),1),"") -> 0 | J17: =IF(OR(H17="",12=""),"",H17*I17) | K17: =IFERROR(_xlfn.XLOOKUP(E17,'ITEM MASTER'!$A:$A,'ITEM MASTER'!$H:$H,""),"") -> 0 | L17: =IF(OR(G17="",H17=""),"",IF(G17="BOTTLE",H17,IF(G17="CARTON",H17*K17,H17))) | O17: =IF(J17="","",J17-N17)
A18: =IF(B18="","","PUR-"&TEXT(ROW()-1,"0000")) | F18: =+IFERROR(_xlfn.XLOOKUP(E18,'ITEM MASTER'!$A:$A,'ITEM MASTER'!$B:$B,""),"") -> 0 | I18: =IFERROR(_xlfn.XLOOKUP(E18,'ITEM MASTER'!$A:$A,'ITEM MASTER'!$I:$I,"")*IF(G18="CARTON",_xlfn.XLOOKUP(E18,'ITEM MASTER'!$A:$A,'ITEM MASTER'!$H:$H,1),1),"") -> 0 | J18: =IF(OR(H18="",12=""),"",H18*I18) | K18: =IFERROR(_xlfn.XLOOKUP(E18,'ITEM MASTER'!$A:$A,'ITEM MASTER'!$H:$H,""),"") -> 0 | L18: =IF(OR(G18="",H18=""),"",IF(G18="BOTTLE",H18,IF(G18="CARTON",H18*K18,H18))) | O18: =IF(J18="","",J18-N18)
A19: =IF(B19="","","PUR-"&TEXT(ROW()-1,"0000")) | F19: =+IFERROR(_xlfn.XLOOKUP(E19,'ITEM MASTER'!$A:$A,'ITEM MASTER'!$B:$B,""),"") -> 0 | I19: =IFERROR(_xlfn.XLOOKUP(E19,'ITEM MASTER'!$A:$A,'ITEM MASTER'!$I:$I,"")*IF(G19="CARTON",_xlfn.XLOOKUP(E19,'ITEM MASTER'!$A:$A,'ITEM MASTER'!$H:$H,1),1),"") -> 0 | J19: =IF(OR(H19="",12=""),"",H19*I19) | K19: =IFERROR(_xlfn.XLOOKUP(E19,'ITEM MASTER'!$A:$A,'ITEM MASTER'!$H:$H,""),"") -> 0 | L19: =IF(OR(G19="",H19=""),"",IF(G19="BOTTLE",H19,IF(G19="CARTON",H19*K19,H19))) | O19: =IF(J19="","",J19-N19)
A20: =IF(B20="","","PUR-"&TEXT(ROW()-1,"0000")) | F20: =+IFERROR(_xlfn.XLOOKUP(E20,'ITEM MASTER'!$A:$A,'ITEM MASTER'!$B:$B,""),"") -> 0 | I20: =IFERROR(_xlfn.XLOOKUP(E20,'ITEM MASTER'!$A:$A,'ITEM MASTER'!$I:$I,"")*IF(G20="CARTON",_xlfn.XLOOKUP(E20,'ITEM MASTER'!$A:$A,'ITEM MASTER'!$H:$H,1),1),"") -> 0 | J20: =IF(OR(H20="",12=""),"",H20*I20) | K20: =IFERROR(_xlfn.XLOOKUP(E20,'ITEM MASTER'!$A:$A,'ITEM MASTER'!$H:$H,""),"") -> 0 | L20: =IF(OR(G20="",H20=""),"",IF(G20="BOTTLE",H20,IF(G20="CARTON",H20*K20,H20))) | O20: =IF(J20="","",J20-N20)
A21: =IF(B21="","","PUR-"&TEXT(ROW()-1,"0000")) | F21: =+IFERROR(_xlfn.XLOOKUP(E21,'ITEM MASTER'!$A:$A,'ITEM MASTER'!$B:$B,""),"") -> 0 | I21: =IFERROR(_xlfn.XLOOKUP(E21,'ITEM MASTER'!$A:$A,'ITEM MASTER'!$I:$I,"")*IF(G21="CARTON",_xlfn.XLOOKUP(E21,'ITEM MASTER'!$A:$A,'ITEM MASTER'!$H:$H,1),1),"") -> 0 | J21: =IF(OR(H21="",12=""),"",H21*I21) | K21: =IFERROR(_xlfn.XLOOKUP(E21,'ITEM MASTER'!$A:$A,'ITEM MASTER'!$H:$H,""),"") -> 0 | L21: =IF(OR(G21="",H21=""),"",IF(G21="BOTTLE",H21,IF(G21="CARTON",H21*K21,H21))) | O21: =IF(J21="","",J21-N21)
... A29: =IF(B29="","","PUR-"&TEXT(ROW()-1,"0000")) | F29: =+IFERROR(_xlfn.XLOOKUP(E29,'ITEM MASTER'!$A:$A,'ITEM MASTER'!$B:$B,""),"") -> 0 | I29: =IFERROR(_xlfn.XLOOKUP(E29,'ITEM MASTER'!$A:$A,'ITEM MASTER'!$I:$I,"")*IF(G29="CARTON",_xlfn.XLOOKUP(E29,'ITEM MASTER'!$A:$A,'ITEM MASTER'!$H:$H,1),1),"") -> 0 | J29: =IF(OR(H29="",12=""),"",H29*I29) | K29: =IFERROR(_xlfn.XLOOKUP(E29,'ITEM MASTER'!$A:$A,'ITEM MASTER'!$H:$H,""),"") -> 0 | L29: =IF(OR(G29="",H29=""),"",IF(G29="BOTTLE",H29,IF(G29="CARTON",H29*K29,H29))) | O29: =IF(J29="","",J29-N29)

Sheet SUPPLIER
A1: SUPPLIER ID | B1: SUPPLIER NAME | C1: CONTACT PERSON | D1: PHONE | E1: CITY | F1: ADDRESS | G1: OPENING PAYABLE | H1: STATUS | I1: REMARKS
A2: SUP-001 | B2: MALIK AYAN SAJID | D2: 3125130252 | E2: LAHORE | F2: BADAMI BAGH | G2: 219600 | H2: ACTIVE
A3: SUP-002 | B3: AFTAB BHATTI | E3: GUJER KHAN | F3: PINDI ROAD | G3: 31000 | H3: ACTIVE

Sheet STOCK LEDGER
A1: DATE | B1: REFERENCE NUMBER | C1: TRANSACTION TYPE | D1: ITEM CODE | E1: PRODUCT NAME | F1: UNIT | G1: QUANTITY | H1: RATE | I1: STOCK IN | J1: STOCK OUT | K1: BALANCE | L1: REMARKS
A2: 46299 | C2: SALE | D2: ATH-001 | E2: =IFERROR(_xlfn.XLOOKUP(D2,'ITEM MASTER'!$A:$A,'ITEM MASTER'!$B:$B,""),"") -> HONDA ATLAS | F2: CARTON | G2: 0 | H2: 5000 | I2: =IF(OR(C2="PURCHASE",C2="OPENING"),G2*IF(F2="CARTON",_xlfn.XLOOKUP(D2,'ITEM MASTER'!$A:$A,'ITEM MASTER'!$H:$H,1),1),0) -> 0 | J2: =IF(C2="SALE",G2*IF(F2="CARTON",_xlfn.XLOOKUP(D2,'ITEM MASTER'!$A:$A,'ITEM MASTER'!$H:$H,1),1),0) -> 0 | K2: =SUMIFS($I$2:I2,$D$2:D2,D2)-SUMIFS($J$2:J2,$D$2:D2,D2) -> 0
E3: =IFERROR(_xlfn.XLOOKUP(D3,'ITEM MASTER'!$A:$A,'ITEM MASTER'!$B:$B,""),"") -> 0 | F3: CARTON | H3: =IFERROR(_xlfn.XLOOKUP(D3,'ITEM MASTER'!$A:$A,'ITEM MASTER'!$I:$I,"")*IF(F3="CARTON",_xlfn.XLOOKUP(D3,'ITEM MASTER'!$A:$A,'ITEM MASTER'!$H:$H,1),1),"") -> 0 | I3: =IF(OR(C3="PURCHASE",C3="OPENING"),G3*IF(F3="CARTON",_xlfn.XLOOKUP(D3,'ITEM MASTER'!$A:$A,'ITEM MASTER'!$H:$H,1),1),0) -> 0 | J3: =IF(C3="SALE",G3*IF(F3="CARTON",_xlfn.XLOOKUP(D3,'ITEM MASTER'!$A:$A,'ITEM MASTER'!$H:$H,1),1),0) -> 0 | K3: =SUMIFS($I$2:I3,$D$2:D3,D3)-SUMIFS($J$2:J3,$D$2:D3,D3) -> 0
E4: =IFERROR(_xlfn.XLOOKUP(D4,'ITEM MASTER'!$A:$A,'ITEM MASTER'!$B:$B,""),"") -> 0 | F4: CARTON | H4: =IFERROR(_xlfn.XLOOKUP(D4,'ITEM MASTER'!$A:$A,'ITEM MASTER'!$I:$I,"")*IF(F4="CARTON",_xlfn.XLOOKUP(D4,'ITEM MASTER'!$A:$A,'ITEM MASTER'!$H:$H,1),1),"") -> 0 | I4: =IF(OR(C4="PURCHASE",C4="OPENING"),G4*IF(F4="CARTON",_xlfn.XLOOKUP(D4,'ITEM MASTER'!$A:$A,'ITEM MASTER'!$H:$H,1),1),0) -> 0 | J4: =IF(C4="SALE",G4*IF(F4="CARTON",_xlfn.XLOOKUP(D4,'ITEM MASTER'!$A:$A,'ITEM MASTER'!$H:$H,1),1),0) -> 0 | K4: =SUMIFS($I$2:I4,$D$2:D4,D4)-SUMIFS($J$2:J4,$D$2:D4,D4) -> 0
E5: =IFERROR(_xlfn.XLOOKUP(D5,'ITEM MASTER'!$A:$A,'ITEM MASTER'!$B:$B,""),"") -> 0 | F5: CARTON | H5: =IFERROR(_xlfn.XLOOKUP(D5,'ITEM MASTER'!$A:$A,'ITEM MASTER'!$I:$I,"")*IF(F5="CARTON",_xlfn.XLOOKUP(D5,'ITEM MASTER'!$A:$A,'ITEM MASTER'!$H:$H,1),1),"") -> 0 | I5: =IF(OR(C5="PURCHASE",C5="OPENING"),G5*IF(F5="CARTON",_xlfn.XLOOKUP(D5,'ITEM MASTER'!$A:$A,'ITEM MASTER'!$H:$H,1),1),0) -> 0 | J5: =IF(C5="SALE",G5*IF(F5="CARTON",_xlfn.XLOOKUP(D5,'ITEM MASTER'!$A:$A,'ITEM MASTER'!$H:$H,1),1),0) -> 0 | K5: =SUMIFS($I$2:I5,$D$2:D5,D5)-SUMIFS($J$2:J5,$D$2:D5,D5) -> 0
A6: 46299 | C6: PURCHASE | D6: ATH-001 | E6: =IFERROR(_xlfn.XLOOKUP(D6,'ITEM MASTER'!$A:$A,'ITEM MASTER'!$B:$B,""),"") -> HONDA ATLAS | F6: CARTON | G6: 1 | H6: =IFERROR(_xlfn.XLOOKUP(D6,'ITEM MASTER'!$A:$A,'ITEM MASTER'!$I:$I,"")*IF(F6="CARTON",_xlfn.XLOOKUP(D6,'ITEM MASTER'!$A:$A,'ITEM MASTER'!$H:$H,1),1),"") -> 4800 | I6: =IF(OR(C6="PURCHASE",C6="OPENING"),G6*IF(F6="CARTON",_xlfn.XLOOKUP(D6,'ITEM MASTER'!$A:$A,'ITEM MASTER'!$H:$H,1),1),0) -> 12 | J6: =IF(C6="SALE",G6*IF(F6="CARTON",_xlfn.XLOOKUP(D6,'ITEM MASTER'!$A:$A,'ITEM MASTER'!$H:$H,1),1),0) -> 0 | K6: =SUMIFS($I$2:I6,$D$2:D6,D6)-SUMIFS($J$2:J6,$D$2:D6,D6) -> 12
E7: =IFERROR(_xlfn.XLOOKUP(D7,'ITEM MASTER'!$A:$A,'ITEM MASTER'!$B:$B,""),"") -> 0 | F7: CARTON | H7: =IFERROR(_xlfn.XLOOKUP(D7,'ITEM MASTER'!$A:$A,'ITEM MASTER'!$I:$I,"")*IF(F7="CARTON",_xlfn.XLOOKUP(D7,'ITEM MASTER'!$A:$A,'ITEM MASTER'!$H:$H,1),1),"") -> 0 | I7: =IF(OR(C7="PURCHASE",C7="OPENING"),G7*IF(F7="CARTON",_xlfn.XLOOKUP(D7,'ITEM MASTER'!$A:$A,'ITEM MASTER'!$H:$H,1),1),0) -> 0 | J7: =IF(C7="SALE",G7*IF(F7="CARTON",_xlfn.XLOOKUP(D7,'ITEM MASTER'!$A:$A,'ITEM MASTER'!$H:$H,1),1),0) -> 0 | K7: =SUMIFS($I$2:I7,$D$2:D7,D7)-SUMIFS($J$2:J7,$D$2:D7,D7) -> 0
E8: =IFERROR(_xlfn.XLOOKUP(D8,'ITEM MASTER'!$A:$A,'ITEM MASTER'!$B:$B,""),"") -> 0 | F8: CARTON | H8: =IFERROR(_xlfn.XLOOKUP(D8,'ITEM MASTER'!$A:$A,'ITEM MASTER'!$I:$I,"")*IF(F8="CARTON",_xlfn.XLOOKUP(D8,'ITEM MASTER'!$A:$A,'ITEM MASTER'!$H:$H,1),1),"") -> 0 | I8: =IF(OR(C8="PURCHASE",C8="OPENING"),G8*IF(F8="CARTON",_xlfn.XLOOKUP(D8,'ITEM MASTER'!$A:$A,'ITEM MASTER'!$H:$H,1),1),0) -> 0 | J8: =IF(C8="SALE",G8*IF(F8="CARTON",_xlfn.XLOOKUP(D8,'ITEM MASTER'!$A:$A,'ITEM MASTER'!$H:$H,1),1),0) -> 0 | K8: =SUMIFS($I$2:I8,$D$2:D8,D8)-SUMIFS($J$2:J8,$D$2:D8,D8) -> 0
E9: =IFERROR(_xlfn.XLOOKUP(D9,'ITEM MASTER'!$A:$A,'ITEM MASTER'!$B:$B,""),"") -> 0 | F9: CARTON | H9: =IFERROR(_xlfn.XLOOKUP(D9,'ITEM MASTER'!$A:$A,'ITEM MASTER'!$I:$I,"")*IF(F9="CARTON",_xlfn.XLOOKUP(D9,'ITEM MASTER'!$A:$A,'ITEM MASTER'!$H:$H,1),1),"") -> 0 | I9: =IF(OR(C9="PURCHASE",C9="OPENING"),G9*IF(F9="CARTON",_xlfn.XLOOKUP(D9,'ITEM MASTER'!$A:$A,'ITEM MASTER'!$H:$H,1),1),0) -> 0 | J9: =IF(C9="SALE",G9*IF(F9="CARTON",_xlfn.XLOOKUP(D9,'ITEM MASTER'!$A:$A,'ITEM MASTER'!$H:$H,1),1),0) -> 0 | K9: =SUMIFS($I$2:I9,$D$2:D9,D9)-SUMIFS($J$2:J9,$D$2:D9,D9) -> 0
E10: =IFERROR(_xlfn.XLOOKUP(D10,'ITEM MASTER'!$A:$A,'ITEM MASTER'!$B:$B,""),"") -> 0 | F10: CARTON | H10: =IFERROR(_xlfn.XLOOKUP(D10,'ITEM MASTER'!$A:$A,'ITEM MASTER'!$I:$I,"")*IF(F10="CARTON",_xlfn.XLOOKUP(D10,'ITEM MASTER'!$A:$A,'ITEM MASTER'!$H:$H,1),1),"") -> 0 | I10: =IF(OR(C10="PURCHASE",C10="OPENING"),G10*IF(F10="CARTON",_xlfn.XLOOKUP(D10,'ITEM MASTER'!$A:$A,'ITEM MASTER'!$H:$H,1),1),0) -> 0 | J10: =IF(C10="SALE",G10*IF(F10="CARTON",_xlfn.XLOOKUP(D10,'ITEM MASTER'!$A:$A,'ITEM MASTER'!$H:$H,1),1),0) -> 0 | K10: =SUMIFS($I$2:I10,$D$2:D10,D10)-SUMIFS($J$2:J10,$D$2:D10,D10) -> 0
E11: =IFERROR(_xlfn.XLOOKUP(D11,'ITEM MASTER'!$A:$A,'ITEM MASTER'!$B:$B,""),"") -> 0 | F11: CARTON | H11: =IFERROR(_xlfn.XLOOKUP(D11,'ITEM MASTER'!$A:$A,'ITEM MASTER'!$I:$I,"")*IF(F11="CARTON",_xlfn.XLOOKUP(D11,'ITEM MASTER'!$A:$A,'ITEM MASTER'!$H:$H,1),1),"") -> 0 | I11: =IF(OR(C11="PURCHASE",C11="OPENING"),G11*IF(F11="CARTON",_xlfn.XLOOKUP(D11,'ITEM MASTER'!$A:$A,'ITEM MASTER'!$H:$H,1),1),0) -> 0 | J11: =IF(C11="SALE",G11*IF(F11="CARTON",_xlfn.XLOOKUP(D11,'ITEM MASTER'!$A:$A,'ITEM MASTER'!$H:$H,1),1),0) -> 0 | K11: =SUMIFS($I$2:I11,$D$2:D11,D11)-SUMIFS($J$2:J11,$D$2:D11,D11) -> 0
E12: =IFERROR(_xlfn.XLOOKUP(D12,'ITEM MASTER'!$A:$A,'ITEM MASTER'!$B:$B,""),"") -> 0 | F12: CARTON | H12: =IFERROR(_xlfn.XLOOKUP(D12,'ITEM MASTER'!$A:$A,'ITEM MASTER'!$I:$I,"")*IF(F12="CARTON",_xlfn.XLOOKUP(D12,'ITEM MASTER'!$A:$A,'ITEM MASTER'!$H:$H,1),1),"") -> 0 | I12: =IF(OR(C12="PURCHASE",C12="OPENING"),G12*IF(F12="CARTON",_xlfn.XLOOKUP(D12,'ITEM MASTER'!$A:$A,'ITEM MASTER'!$H:$H,1),1),0) -> 0 | J12: =IF(C12="SALE",G12*IF(F12="CARTON",_xlfn.XLOOKUP(D12,'ITEM MASTER'!$A:$A,'ITEM MASTER'!$H:$H,1),1),0) -> 0 | K12: =SUMIFS($I$2:I12,$D$2:D12,D12)-SUMIFS($J$2:J12,$D$2:D12,D12) -> 0
E13: =IFERROR(_xlfn.XLOOKUP(D13,'ITEM MASTER'!$A:$A,'ITEM MASTER'!$B:$B,""),"") -> 0 | F13: CARTON | H13: =IFERROR(_xlfn.XLOOKUP(D13,'ITEM MASTER'!$A:$A,'ITEM MASTER'!$I:$I,"")*IF(F13="CARTON",_xlfn.XLOOKUP(D13,'ITEM MASTER'!$A:$A,'ITEM MASTER'!$H:$H,1),1),"") -> 0 | I13: =IF(OR(C13="PURCHASE",C13="OPENING"),G13*IF(F13="CARTON",_xlfn.XLOOKUP(D13,'ITEM MASTER'!$A:$A,'ITEM MASTER'!$H:$H,1),1),0) -> 0 | J13: =IF(C13="SALE",G13*IF(F13="CARTON",_xlfn.XLOOKUP(D13,'ITEM MASTER'!$A:$A,'ITEM MASTER'!$H:$H,1),1),0) -> 0 | K13: =SUMIFS($I$2:I13,$D$2:D13,D13)-SUMIFS($J$2:J13,$D$2:D13,D13) -> 0
E14: =IFERROR(_xlfn.XLOOKUP(D14,'ITEM MASTER'!$A:$A,'ITEM MASTER'!$B:$B,""),"") -> 0 | F14: CARTON | H14: =IFERROR(_xlfn.XLOOKUP(D14,'ITEM MASTER'!$A:$A,'ITEM MASTER'!$I:$I,"")*IF(F14="CARTON",_xlfn.XLOOKUP(D14,'ITEM MASTER'!$A:$A,'ITEM MASTER'!$H:$H,1),1),"") -> 0 | I14: =IF(OR(C14="PURCHASE",C14="OPENING"),G14*IF(F14="CARTON",_xlfn.XLOOKUP(D14,'ITEM MASTER'!$A:$A,'ITEM MASTER'!$H:$H,1),1),0) -> 0 | J14: =IF(C14="SALE",G14*IF(F14="CARTON",_xlfn.XLOOKUP(D14,'ITEM MASTER'!$A:$A,'ITEM MASTER'!$H:$H,1),1),0) -> 0 | K14: =SUMIFS($I$2:I14,$D$2:D14,D14)-SUMIFS($J$2:J14,$D$2:D14,D14) -> 0
E15: =IFERROR(_xlfn.XLOOKUP(D15,'ITEM MASTER'!$A:$A,'ITEM MASTER'!$B:$B,""),"") -> 0 | F15: CARTON | H15: =IFERROR(_xlfn.XLOOKUP(D15,'ITEM MASTER'!$A:$A,'ITEM MASTER'!$I:$I,"")*IF(F15="CARTON",_xlfn.XLOOKUP(D15,'ITEM MASTER'!$A:$A,'ITEM MASTER'!$H:$H,1),1),"") -> 0 | I15: =IF(OR(C15="PURCHASE",C15="OPENING"),G15*IF(F15="CARTON",_xlfn.XLOOKUP(D15,'ITEM MASTER'!$A:$A,'ITEM MASTER'!$H:$H,1),1),0) -> 0 | J15: =IF(C15="SALE",G15*IF(F15="CARTON",_xlfn.XLOOKUP(D15,'ITEM MASTER'!$A:$A,'ITEM MASTER'!$H:$H,1),1),0) -> 0 | K15: =SUMIFS($I$2:I15,$D$2:D15,D15)-SUMIFS($J$2:J15,$D$2:D15,D15) -> 0
E16: =IFERROR(_xlfn.XLOOKUP(D16,'ITEM MASTER'!$A:$A,'ITEM MASTER'!$B:$B,""),"") -> 0 | F16: CARTON | H16: =IFERROR(_xlfn.XLOOKUP(D16,'ITEM MASTER'!$A:$A,'ITEM MASTER'!$I:$I,"")*IF(F16="CARTON",_xlfn.XLOOKUP(D16,'ITEM MASTER'!$A:$A,'ITEM MASTER'!$H:$H,1),1),"") -> 0 | I16: =IF(OR(C16="PURCHASE",C16="OPENING"),G16*IF(F16="CARTON",_xlfn.XLOOKUP(D16,'ITEM MASTER'!$A:$A,'ITEM MASTER'!$H:$H,1),1),0) -> 0 | J16: =IF(C16="SALE",G16*IF(F16="CARTON",_xlfn.XLOOKUP(D16,'ITEM MASTER'!$A:$A,'ITEM MASTER'!$H:$H,1),1),0) -> 0 | K16: =SUMIFS($I$2:I16,$D$2:D16,D16)-SUMIFS($J$2:J16,$D$2:D16,D16) -> 0
E17: =IFERROR(_xlfn.XLOOKUP(D17,'ITEM MASTER'!$A:$A,'ITEM MASTER'!$B:$B,""),"") -> 0 | F17: CARTON | H17: =IFERROR(_xlfn.XLOOKUP(D17,'ITEM MASTER'!$A:$A,'ITEM MASTER'!$I:$I,"")*IF(F17="CARTON",_xlfn.XLOOKUP(D17,'ITEM MASTER'!$A:$A,'ITEM MASTER'!$H:$H,1),1),"") -> 0 | I17: =IF(OR(C17="PURCHASE",C17="OPENING"),G17*IF(F17="CARTON",_xlfn.XLOOKUP(D17,'ITEM MASTER'!$A:$A,'ITEM MASTER'!$H:$H,1),1),0) -> 0 | J17: =IF(C17="SALE",G17*IF(F17="CARTON",_xlfn.XLOOKUP(D17,'ITEM MASTER'!$A:$A,'ITEM MASTER'!$H:$H,1),1),0) -> 0 | K17: =SUMIFS($I$2:I17,$D$2:D17,D17)-SUMIFS($J$2:J17,$D$2:D17,D17) -> 0
E18: =IFERROR(_xlfn.XLOOKUP(D18,'ITEM MASTER'!$A:$A,'ITEM MASTER'!$B:$B,""),"") -> 0 | F18: CARTON | H18: =IFERROR(_xlfn.XLOOKUP(D18,'ITEM MASTER'!$A:$A,'ITEM MASTER'!$I:$I,"")*IF(F18="CARTON",_xlfn.XLOOKUP(D18,'ITEM MASTER'!$A:$A,'ITEM MASTER'!$H:$H,1),1),"") -> 0 | I18: =IF(OR(C18="PURCHASE",C18="OPENING"),G18*IF(F18="CARTON",_xlfn.XLOOKUP(D18,'ITEM MASTER'!$A:$A,'ITEM MASTER'!$H:$H,1),1),0) -> 0 | J18: =IF(C18="SALE",G18*IF(F18="CARTON",_xlfn.XLOOKUP(D18,'ITEM MASTER'!$A:$A,'ITEM MASTER'!$H:$H,1),1),0) -> 0 | K18: =SUMIFS($I$2:I18,$D$2:D18,D18)-SUMIFS($J$2:J18,$D$2:D18,D18) -> 0
... E615: =IFERROR(_xlfn.XLOOKUP(D615,'ITEM MASTER'!$A:$A,'ITEM MASTER'!$B:$B,""),"") -> 0 | F615: CARTON | H615: =IFERROR(_xlfn.XLOOKUP(D615,'ITEM MASTER'!$A:$A,'ITEM MASTER'!$I:$I,"")*IF(F615="CARTON",_xlfn.XLOOKUP(D615,'ITEM MASTER'!$A:$A,'ITEM MASTER'!$H:$H,1),1),"") -> 0 | I615: =IF(OR(C615="PURCHASE",C615="OPENING"),G615*IF(F615="CARTON",_xlfn.XLOOKUP(D615,'ITEM MASTER'!$A:$A,'ITEM MASTER'!$H:$H,1),1),0) -> 0 | J615: =IF(C615="SALE",G615*IF(F615="CARTON",_xlfn.XLOOKUP(D615,'ITEM MASTER'!$A:$A,'ITEM MASTER'!$H:$H,1),1),0) -> 0 | K615: =SUMIFS($I$2:I615,$D$2:D615,D615)-SUMIFS($J$2:J615,$D$2:D615,D615) -> 0

Sheet SALES
A1: Column1 | B1: Column2 | C1: Column3 | D1: Column4 | E1: Column5 | F1: Column6 | G1: Column7 | H1: Column8 | I1: Column9 | J1: Column10 | K1: Column11 | L1: Column12 | M1: Column13 | N1: Column14 | O1: Column15 | P1: Column16
A2: SALE ID | B2: DATE | C2: CUSTOMER | D2: INVOICE NO | E2: ITEM CODE | F2: PRODUCT NAME | G2: SALE UNIT | H2: QUANTITY | I2: RATE | J2: TOTAL AMOUNT | K2: CONVERSION | L2: BASE QUANTITY | M2: PAYMENT STATUS | N2: RECEIVED AMOUNT | O2: RECEIVEABLE | P2: REMARKS
A3: ="SAL-"&ROW()-1 -> SAL-2 | B3: 46301 | E3: ATH-001 | F3: =IFERROR(_xlfn.XLOOKUP(E3,'ITEM MASTER'!$A:$A,'ITEM MASTER'!$B:$B,""),"") -> HONDA ATLAS | G3: CARTON | H3: 1 | I3: 5000 | J3: =IF(OR(H3="",12=""),"",H3*I3) -> 5000 | K3: =IFERROR(_xlfn.XLOOKUP(E3,'ITEM MASTER'!$A:$A,'ITEM MASTER'!$H:$H,""),"") -> 12 | L3: =IF(OR(G3="",H3=""),"",IF(G3="BOTTLE",H3,IF(G3="CARTON",H3*K3,H3))) -> 12 | M3: PAID | N3: 5000 | O3: =IF(J3="","",J3-N3) -> 0
A4: ="SAL-"&ROW()-1 -> SAL-3 | B4: 46302 | E4: ATH-001 | F4: =IFERROR(_xlfn.XLOOKUP(E4,'ITEM MASTER'!$A:$A,'ITEM MASTER'!$B:$B,""),"") -> HONDA ATLAS | G4: BOTTLE | H4: 26 | I4: 450 | J4: =IF(OR(H4="",12=""),"",H4*I4) -> 11700 | K4: =IFERROR(_xlfn.XLOOKUP(E4,'ITEM MASTER'!$A:$A,'ITEM MASTER'!$H:$H,""),"") -> 12 | L4: =IF(OR(G4="",H4=""),"",IF(G4="BOTTLE",H4,IF(G4="CARTON",H4*K4,H4))) -> 26 | M4: PAID | N4: 11700 | O4: =IF(J4="","",J4-N4) -> 0
A5: ="SAL-"&ROW()-1 -> SAL-4 | E5: ATH-003 | F5: =IFERROR(_xlfn.XLOOKUP(E5,'ITEM MASTER'!$A:$A,'ITEM MASTER'!$B:$B,""),"") -> HONDA ATLAS | G5: CARTON | H5: 3 | I5: 5000 | J5: =IF(OR(H5="",12=""),"",H5*I5) -> 15000 | K5: =IFERROR(_xlfn.XLOOKUP(E5,'ITEM MASTER'!$A:$A,'ITEM MASTER'!$H:$H,""),"") -> 12 | L5: =IF(OR(G5="",H5=""),"",IF(G5="BOTTLE",H5,IF(G5="CARTON",H5*K5,H5))) -> 36 | M5: PARTIAL | N5: 12000 | O5: =IF(J5="","",J5-N5) -> 3000
A6: ="SAL-"&ROW()-1 -> SAL-5 | E6: ATH-006 | F6: =IFERROR(_xlfn.XLOOKUP(E6,'ITEM MASTER'!$A:$A,'ITEM MASTER'!$B:$B,""),"") -> DYL LUBE | G6: BOTTLE | H6: 10 | I6: 400 | J6: =IF(OR(H6="",12=""),"",H6*I6) -> 4000 | K6: =IFERROR(_xlfn.XLOOKUP(E6,'ITEM MASTER'!$A:$A,'ITEM MASTER'!$H:$H,""),"") -> 12 | L6: =IF(OR(G6="",H6=""),"",IF(G6="BOTTLE",H6,IF(G6="CARTON",H6*K6,H6))) -> 10 | M6: PARTIAL | N6: 2000 | O6: =IF(J6="","",J6-N6) -> 2000
A7: ="SAL-"&ROW()-1 -> SAL-6 | E7: ATH-003 | F7: =IFERROR(_xlfn.XLOOKUP(E7,'ITEM MASTER'!$A:$A,'ITEM MASTER'!$B:$B,""),"") -> HONDA ATLAS | G7: CARTON | H7: 3 | I7: 450 | J7: =IF(OR(H7="",12=""),"",H7*I7) -> 1350 | K7: =IFERROR(_xlfn.XLOOKUP(E7,'ITEM MASTER'!$A:$A,'ITEM MASTER'!$H:$H,""),"") -> 12 | L7: =IF(OR(G7="",H7=""),"",IF(G7="BOTTLE",H7,IF(G7="CARTON",H7*K7,H7))) -> 36 | M7: PARTIAL | N7: 900 | O7: =IF(J7="","",J7-N7) -> 450
A8: ="SAL-"&ROW()-1 -> SAL-7 | E8: ATH-007 | F8: =IFERROR(_xlfn.XLOOKUP(E8,'ITEM MASTER'!$A:$A,'ITEM MASTER'!$B:$B,""),"") | J8: =IF(OR(H8="",12=""),"",H8*I8) | K8: =IFERROR(_xlfn.XLOOKUP(E8,'ITEM MASTER'!$A:$A,'ITEM MASTER'!$H:$H,""),"") | L8: =IF(OR(G8="",H8=""),"",IF(G8="BOTTLE",H8,IF(G8="CARTON",H8*K8,H8))) | O8: =IF(J8="","",J8-N8)
A9: ="SAL-"&ROW()-1 -> SAL-8 | E9: ATH-008 | F9: =IFERROR(_xlfn.XLOOKUP(E9,'ITEM MASTER'!$A:$A,'ITEM MASTER'!$B:$B,""),"") | J9: =IF(OR(H9="",12=""),"",H9*I9) | K9: =IFERROR(_xlfn.XLOOKUP(E9,'ITEM MASTER'!$A:$A,'ITEM MASTER'!$H:$H,""),"") | L9: =IF(OR(G9="",H9=""),"",IF(G9="BOTTLE",H9,IF(G9="CARTON",H9*K9,H9))) | O9: =IF(J9="","",J9-N9)
A10: ="SAL-"&ROW()-1 -> SAL-9 | E10: ATH-009 | F10: =IFERROR(_xlfn.XLOOKUP(E10,'ITEM MASTER'!$A:$A,'ITEM MASTER'!$B:$B,""),"") | J10: =IF(OR(H10="",12=""),"",H10*I10) | K10: =IFERROR(_xlfn.XLOOKUP(E10,'ITEM MASTER'!$A:$A,'ITEM MASTER'!$H:$H,""),"") | L10: =IF(OR(G10="",H10=""),"",IF(G10="BOTTLE",H10,IF(G10="CARTON",H10*K10,H10))) | O10: =IF(J10="","",J10-N10)
A11: ="SAL-"&ROW()-1 -> SAL-10 | F11: =IFERROR(_xlfn.XLOOKUP(E11,'ITEM MASTER'!$A:$A,'ITEM MASTER'!$B:$B,""),"") -> 0 | J11: =IF(OR(H11="",12=""),"",H11*I11) | K11: =IFERROR(_xlfn.XLOOKUP(E11,'ITEM MASTER'!$A:$A,'ITEM MASTER'!$H:$H,""),"") -> 0 | L11: =IF(OR(G11="",H11=""),"",IF(G11="BOTTLE",H11,IF(G11="CARTON",H11*K11,H11))) | O11: =IF(J11="","",J11-N11)
A12: ="SAL-"&ROW()-1 -> SAL-11 | F12: =IFERROR(_xlfn.XLOOKUP(E12,'ITEM MASTER'!$A:$A,'ITEM MASTER'!$B:$B,""),"") -> 0 | J12: =IF(OR(H12="",12=""),"",H12*I12) | K12: =IFERROR(_xlfn.XLOOKUP(E12,'ITEM MASTER'!$A:$A,'ITEM MASTER'!$H:$H,""),"") -> 0 | L12: =IF(OR(G12="",H12=""),"",IF(G12="BOTTLE",H12,IF(G12="CARTON",H12*K12,H12))) | O12: =IF(J12="","",J12-N12)
A13: ="SAL-"&ROW()-1 -> SAL-12 | F13: =IFERROR(_xlfn.XLOOKUP(E13,'ITEM MASTER'!$A:$A,'ITEM MASTER'!$B:$B,""),"") -> 0 | J13: =IF(OR(H13="",12=""),"",H13*I13) | K13: =IFERROR(_xlfn.XLOOKUP(E13,'ITEM MASTER'!$A:$A,'ITEM MASTER'!$H:$H,""),"") -> 0 | L13: =IF(OR(G13="",H13=""),"",IF(G13="BOTTLE",H13,IF(G13="CARTON",H13*K13,H13))) | O13: =IF(J13="","",J13-N13)
A14: ="SAL-"&ROW()-1 -> SAL-13 | F14: =IFERROR(_xlfn.XLOOKUP(E14,'ITEM MASTER'!$A:$A,'ITEM MASTER'!$B:$B,""),"") -> 0 | J14: =IF(OR(H14="",12=""),"",H14*I14) | K14: =IFERROR(_xlfn.XLOOKUP(E14,'ITEM MASTER'!$A:$A,'ITEM MASTER'!$H:$H,""),"") -> 0 | L14: =IF(OR(G14="",H14=""),"",IF(G14="BOTTLE",H14,IF(G14="CARTON",H14*K14,H14))) | O14: =IF(J14="","",J14-N14)
A15: ="SAL-"&ROW()-1 -> SAL-14 | F15: =IFERROR(_xlfn.XLOOKUP(E15,'ITEM MASTER'!$A:$A,'ITEM MASTER'!$B:$B,""),"") -> 0 | J15: =IF(OR(H15="",12=""),"",H15*I15) | K15: =IFERROR(_xlfn.XLOOKUP(E15,'ITEM MASTER'!$A:$A,'ITEM MASTER'!$H:$H,""),"") -> 0 | L15: =IF(OR(G15="",H15=""),"",IF(G15="BOTTLE",H15,IF(G15="CARTON",H15*K15,H15))) | O15: =IF(J15="","",J15-N15)
N20: =IFERROR(_xlfn.XLOOKUP(E3,'ITEM MASTER'!$A:$A,'ITEM MASTER'!$J:$J,"")*IF(G3="CARTON",_xlfn.XLOOKUP(E3,'ITEM MASTER'!$A:$A,'ITEM MASTER'!$H:$H,1),1),"") -> 0

Sheet CUSTOMERS
A1: CUSTOMER ID | B1: CUSTOMER | C1: CONTACT PERSON | D1: PHONE | E1: CITY | F1: ADDRESS | G1: OPENING RECEIVEABLE | H1: CREDIT LIMIT | I1: STATUS | J1: REMARKS
A2: ="CUS-"&ROW()-1 -> CUS-1 | B2: SAEED | C2: SAEED AUTOS | D2: 3045464807 | E2: KHOUR | F2: COMPANY CHOWK | G2: 70000 | H2: 30000 | I2: ACTIVE
A3: ="CUS-"&ROW()-1 -> CUS-2 | B3: MEHTAB | C3: SHEIKH AUTOS | E3: JAND
A4: ="CUS-"&ROW()-1 -> CUS-3 | B4: FAYYAZ | C4: FAYYAZ AUTOS | E4: KHOUR
A5: ="CUS-"&ROW()-1 -> CUS-4 | B5: QAZI | C5: QAZI AUTOS | E5: PINDIGHEB
A6: ="CUS-"&ROW()-1 -> CUS-5
A7: ="CUS-"&ROW()-1 -> CUS-6
A8: ="CUS-"&ROW()-1 -> CUS-7
A9: ="CUS-"&ROW()-1 -> CUS-8
A10: ="CUS-"&ROW()-1 -> CUS-9
A11: ="CUS-"&ROW()-1 -> CUS-10
A12: ="CUS-"&ROW()-1 -> CUS-11
A13: ="CUS-"&ROW()-1 -> CUS-12
A14: ="CUS-"&ROW()-1 -> CUS-13
A15: ="CUS-"&ROW()-1 -> CUS-14
A16: ="CUS-"&ROW()-1 -> CUS-15

Sheet CUSTOMERS PAYMENTS
A1: PAYMENT DATE | B1: RECEIPT NO | C1: CUSTOMER | D1: PAYMENT METHOD | E1: REFERENCE | F1: AMOUNT | G1: REMARKS
A2: 46301 | B2: REC-001 | C2: SAEED | D2: CASH | E2: TEST | F2: 10000
A3: 46302 | B3: REC-002 | C3: FAYYAZ | D3: EASYPAISA | E3: TEST | F3: 39000
B4: REC-003
B5: REC-004
B6: REC-005
B7: REC-006
B8: REC-007
B9: REC-008
B10: REC-009
B11: REC-010
B12: REC-011
B13: REC-012
B14: REC-013
B15: REC-014
... B17: REC-016

Sheet EXPENSES
A1: EXPENSE DATE | B1: EXPENSE ID | C1: EXPENSE CATEGORY | D1: DESCRIPTION | E1: PAYMENT METHOD | F1: AMOUNT | G1: PAID TO | H1: REFERENCE | I1: REMARKS | K1: PAYMENT METHOD | L1: TOTAL EXPENSES
A2: 46301 | B2: EXP-001 | C2: FUEL | E2: CASH | F2: 500 | K2: CASH | L2: =SUMIF($E$2:$E$500,K2,$F$2:$F$500) -> 1000
A3: 46302 | B3: EXP-002 | C3: VAHICLE MAINTENANCE | D3: BRAKES | E3: CASH | F3: 500 | G3: TEST | H3: TEST | I3: TEST | K3: BANK | L3: =SUMIF($E$2:$E$500,K3,$F$2:$F$500) -> 1000
B4: EXP-003 | C4: SALARY | D4: SAJID | E4: BANK | F4: 1000 | K4: EASYPAISA | L4: =SUMIF($E$2:$E$500,K4,$F$2:$F$500) -> 0
B5: EXP-004 | C5: RENT | D5: SHOP | E5: OTHER | F5: 35000 | K5: JAZZCASH | L5: =SUMIF($E$2:$E$500,K5,$F$2:$F$500) -> 0
B6: EXP-005 | K6: OTHER | L6: =SUMIF($E$2:$E$500,K6,$F$2:$F$500) -> 35000
B7: EXP-006
B8: EXP-007
B9: EXP-008
B10: EXP-009
B11: EXP-010
B12: EXP-011
B13: EXP-012
B14: EXP-013
B15: EXP-014
B16: EXP-015
B17: EXP-016
B18: EXP-017
... B21: EXP-020

Sheet SUPPLIER PAYMENTS
A1: PAYMENT DATE | B1: PAYMENT ID | C1: SUPPLIER | D1: PAYMENT METHOD | E1: REFERENCE | F1: AMOUNT | G1: REMARKS
B2: SP-001

Sheet CASH & BANK
A1: DATE | B1: TRANSACTION ID | C1: ACCOUNT | D1: TRANSACTION TYPE | E1: DESCRIPTION | F1: REFERENCE | G1: MONEY IN | H1: MONEY OUT | I1: BALANCE | J1: REMARKS | K1: TRANSFER | M1: ACCOUNT | N1: CURRENT BALANCE
A2: 46301 | B2: ="CB-"&TEXT(ROW()-1,"0000") -> CB-0001 | C2: CASH | D2: CAPITAL | E2: OPENING CASH BALANCE | F2: OPENING | G2: 500 | I2: =SUMIFS($G$2:G2,$C$2:C2,C2)-SUMIFS($H$2:H2,$C$2:C2,C2) -> 500 | M2: CASH | N2: =SUMIF($C$2:$C$500,M2,$G$2:$G$500)-SUMIF($C$2:$C$500,M2,$H$2:$H$500)+SUMIF($K$2:$K$500,M2,$H$2:$H$500) -> 80000
B3: ="CB-"&TEXT(ROW()-1,"0000") -> CB-0002 | C3: CASH | D3: CAPITAL | E3: OPENING CASH BALANCE | F3: OPENING | G3: 90000 | I3: =SUMIFS($G$2:G3,$C$2:C3,C3)-SUMIFS($H$2:H3,$C$2:C3,C3) -> 90500 | M3: BANK | N3: =SUMIF($C$2:$C$500,M3,$G$2:$G$500)-SUMIF($C$2:$C$500,M3,$H$2:$H$500)+SUMIF($K$2:$K$500,M3,$H$2:$H$500) -> 47500
A4: 46302 | B4: ="CB-"&TEXT(ROW()-1,"0000") -> CB-0003 | C4: CASH | D4: CUSTOMER PAYMENT | E4: SAEED | F4: REC-001 | G4: 7000 | I4: =SUMIFS($G$2:G4,$C$2:C4,C4)-SUMIFS($H$2:H4,$C$2:C4,C4) -> 97500 | M4: EASYPAISA | N4: =SUMIF($C$2:$C$500,M4,$G$2:$G$500)-SUMIF($C$2:$C$500,M4,$H$2:$H$500)+SUMIF($K$2:$K$500,M4,$H$2:$H$500) -> 10000
B5: ="CB-"&TEXT(ROW()-1,"0000") -> CB-0004 | C5: EASYPAISA | D5: CUSTOMER PAYMENT | E5: FAYYAZ | F5: REC-002 | G5: 40000 | I5: =SUMIFS($G$2:G5,$C$2:C5,C5)-SUMIFS($H$2:H5,$C$2:C5,C5) -> 40000 | M5: JAZZCASH | N5: =SUMIF($C$2:$C$500,M5,$G$2:$G$500)-SUMIF($C$2:$C$500,M5,$H$2:$H$500)+SUMIF($K$2:$K$500,M5,$H$2:$H$500) -> 13000
B6: ="CB-"&TEXT(ROW()-1,"0000") -> CB-0005 | C6: JAZZCASH | D6: CUSTOMER PAYMENT | E6: SAEED | F6: REC-003 | G6: 13000 | I6: =SUMIFS($G$2:G6,$C$2:C6,C6)-SUMIFS($H$2:H6,$C$2:C6,C6) -> 13000 | M6: OTHER | N6: =SUMIF($C$2:$C$500,M6,$G$2:$G$500)-SUMIF($C$2:$C$500,M6,$H$2:$H$500)+SUMIF($K$2:$K$500,M6,$H$2:$H$500) -> 0
B7: ="CB-"&TEXT(ROW()-1,"0000") -> CB-0006 | C7: CASH | D7: TRANSFER | E7: TO BANK | H7: 10000 | I7: =SUMIFS($G$2:G7,$C$2:C7,C7)-SUMIFS($H$2:H7,$C$2:C7,C7) -> 87500 | K7: BANK
B8: ="CB-"&TEXT(ROW()-1,"0000") -> CB-0007 | C8: EASYPAISA | D8: TRANSFER | E8: TO BANK | H8: 30000 | I8: =SUMIFS($G$2:G8,$C$2:C8,C8)-SUMIFS($H$2:H8,$C$2:C8,C8) -> 10000 | K8: BANK | M8: TOTAL AMOUNT | N8: =SUM(N2:N5) -> 150500
B9: ="CB-"&TEXT(ROW()-1,"0000") -> CB-0008 | C9: CASH | D9: TRANSFER | E9: TO BANK | H9: 7500 | I9: =SUMIFS($G$2:G9,$C$2:C9,C9)-SUMIFS($H$2:H9,$C$2:C9,C9) -> 80000 | K9: BANK
B10: ="CB-"&TEXT(ROW()-1,"0000") -> CB-0009 | I10: =SUMIFS($G$2:G10,$C$2:C10,C10)-SUMIFS($H$2:H10,$C$2:C10,C10) -> 0
B11: ="CB-"&TEXT(ROW()-1,"0000") -> CB-0010 | I11: =SUMIFS($G$2:G11,$C$2:C11,C11)-SUMIFS($H$2:H11,$C$2:C11,C11) -> 0
B12: ="CB-"&TEXT(ROW()-1,"0000") -> CB-0011 | I12: =SUMIFS($G$2:G12,$C$2:C12,C12)-SUMIFS($H$2:H12,$C$2:C12,C12) -> 0
B13: ="CB-"&TEXT(ROW()-1,"0000") -> CB-0012 | I13: =SUMIFS($G$2:G13,$C$2:C13,C13)-SUMIFS($H$2:H13,$C$2:C13,C13) -> 0
B14: ="CB-"&TEXT(ROW()-1,"0000") -> CB-0013 | I14: =SUMIFS($G$2:G14,$C$2:C14,C14)-SUMIFS($H$2:H14,$C$2:C14,C14) -> 0
B15: ="CB-"&TEXT(ROW()-1,"0000") -> CB-0014 | I15: =SUMIFS($G$2:G15,$C$2:C15,C15)-SUMIFS($H$2:H15,$C$2:C15,C15) -> 0
B16: ="CB-"&TEXT(ROW()-1,"0000") -> CB-0015 | I16: =SUMIFS($G$2:G16,$C$2:C16,C16)-SUMIFS($H$2:H16,$C$2:C16,C16) -> 0
B17: ="CB-"&TEXT(ROW()-1,"0000") -> CB-0016 | I17: =SUMIFS($G$2:G17,$C$2:C17,C17)-SUMIFS($H$2:H17,$C$2:C17,C17) -> 0
B18: ="CB-"&TEXT(ROW()-1,"0000") -> CB-0017 | I18: =SUMIFS($G$2:G18,$C$2:C18,C18)-SUMIFS($H$2:H18,$C$2:C18,C18) -> 0
B19: ="CB-"&TEXT(ROW()-1,"0000") -> CB-0018 | I19: =SUMIFS($G$2:G19,$C$2:C19,C19)-SUMIFS($H$2:H19,$C$2:C19,C19) -> 0
B20: ="CB-"&TEXT(ROW()-1,"0000") -> CB-0019 | I20: =SUMIFS($G$2:G20,$C$2:C20,C20)-SUMIFS($H$2:H20,$C$2:C20,C20) -> 0
B21: ="CB-"&TEXT(ROW()-1,"0000") -> CB-0020 | I21: =SUMIFS($G$2:G21,$C$2:C21,C21)-SUMIFS($H$2:H21,$C$2:C21,C21) -> 0
B22: ="CB-"&TEXT(ROW()-1,"0000") -> CB-0021 | I22: =SUMIFS($G$2:G22,$C$2:C22,C22)-SUMIFS($H$2:H22,$C$2:C22,C22) -> 0
B23: ="CB-"&TEXT(ROW()-1,"0000") -> CB-0022
